robocorp/http/__init__.py
robocorp/http/_http.py
robocorp/http/py.typed
robocorp_http-0.4.1.dist-info/METADATA
robocorp_http-0.4.1.dist-info/WHEEL
robocorp_http-0.4.1.dist-info/RECORD
